.gitignore
.project
.pydevproject
README.md
setup.py
mediatumfsm/__init__.py
mediatumfsm/_fsm.py
mediatumfsm/compat.py
mediatumfsm/fsm.py
mediatumfsm/sessionfsm.py
mediatumfsm.egg-info/PKG-INFO
mediatumfsm.egg-info/SOURCES.txt
mediatumfsm.egg-info/dependency_links.txt
mediatumfsm.egg-info/pbr.json
mediatumfsm.egg-info/requires.txt
mediatumfsm.egg-info/top_level.txt
mediatumfsm/test/__init__.py
mediatumfsm/test/accumulatorfsm.py
mediatumfsm/test/lightbulbfsm.py
mediatumfsm/test/regexfsm.py
mediatumfsm/test/test_fsm.py
mediatumfsm/test/test_sessionfsm.py