Metadata-Version: 1.1
Name: mediatumfsm
Version: 0.1
Summary: declarative finite state machine library inspired by Akka FSM and erlang gen_fsm
Home-page: https://mediatumdev.ub.tum.de/projects/mediatum-fsm
Author: Tobias Stenzel
Author-email: tobias.stenzel@tum.de
License: GNU General Public License v3 (GPLv3)
Keywords: state machine fsm declarative dsl
Platform: UNKNOWN
Classifier: Development Status :: 3 - Alpha
Classifier: Intended Audience :: Developers
Classifier: License :: OSI Approved :: GNU General Public License v3 (GPLv3)
Classifier: Programming Language :: Python :: 2
Classifier: Programming Language :: Python :: 2.7
Classifier: Programming Language :: Python :: 3
Classifier: Programming Language :: Python :: 3.2
Classifier: Programming Language :: Python :: 3.3
Classifier: Programming Language :: Python :: 3.4
